hamachi_ssh.py
setup.py
hamachi_ssh.egg-info/PKG-INFO
hamachi_ssh.egg-info/SOURCES.txt
hamachi_ssh.egg-info/dependency_links.txt
hamachi_ssh.egg-info/entry_points.txt
hamachi_ssh.egg-info/top_level.txt