Metadata-Version: 1.1
Name: hamachi-ssh
Version: 1.1
Summary: A helper utility for easy SSH connection to machines on Hamachi
Home-page: https://github.com/iroq/hamachi-ssh
Author: Michał Szewczak
Author-email: UNKNOWN
License: MIT
Download-URL: https://github.com/iroq/hamachi-ssh/archive/v1.1.tar.gz
Keywords: hamachi ssh config hostname update ip
Platform: UNKNOWN
